flimage/__init__.py
flimage/_version.py
flimage/core.py
flimage/image_data.py
flimage/meta.py
flimage/series.py
flimage-0.3.3.dist-info/LICENSE
flimage-0.3.3.dist-info/METADATA
flimage-0.3.3.dist-info/WHEEL
flimage-0.3.3.dist-info/top_level.txt
flimage-0.3.3.dist-info/RECORD
