Metadata-Version: 2.2
Name: flimage
Version: 0.3.3
Summary: library for manipulating fluorescence microscopy series data
Author-email: Paul Müller <dev@craban.de>
License: MIT License
Project-URL: Homepage, https://github.com/RI-imaging/flimage
Keywords: fluorescence microscopy,bleach correction
Classifier: Operating System :: OS Independent
Classifier: Programming Language :: Python :: 3
Classifier: Intended Audience :: Science/Research
Requires-Python: <4,>=3.6
License-File: LICENSE
Requires-Dist: h5py>=2.7.0
Requires-Dist: lmfit>=0.9.8
Requires-Dist: numpy>=1.9.0
Requires-Dist: qpimage>=0.5.1
Requires-Dist: scikit-image>=0.11.0
